tikshort/__init__.py
tikshort/base.py
tikshort-1.0.dist-info/METADATA
tikshort-1.0.dist-info/WHEEL
tikshort-1.0.dist-info/top_level.txt
tikshort-1.0.dist-info/RECORD
