Metadata-Version: 2.1
Name: tikshort
Version: 1.0
Summary: Package to Short any Long Tiktok kVideo
Author: vardxg
Author-email: <dev@vardxg.com>
Keywords: python,shorten
Classifier: Development Status :: 1 - Planning
Classifier: Intended Audience :: Developers
Classifier: Programming Language :: Python :: 3
Classifier: Operating System :: Unix
Classifier: Operating System :: MacOS :: MacOS X
Classifier: Operating System :: Microsoft :: Windows
Requires-Dist: requests
